aiqc/__init__.py
aiqc/datum.py
aiqc/mlops.py
aiqc/orm.py
aiqc/plots.py
aiqc/data/basic_dtypes.csv
aiqc/data/delhi_climate.parquet
aiqc/data/epilepsy.parquet
aiqc/data/exoplanets.parquet
aiqc/data/heart_failure.parquet
aiqc/data/houses.csv
aiqc/data/iris.tsv
aiqc/data/iris_10x.tsv
aiqc/data/iris_noHeaders.csv
aiqc/data/sonar.csv
aiqc/data/spam.csv
aiqc/tests/__init__.py
aiqc/tests/tf_bin_img.py
aiqc/tests/tf_bin_seq.py
aiqc/tests/tf_bin_tab.py
aiqc/tests/tf_fore_img.py
aiqc/tests/tf_fore_tab.py
aiqc/tests/tf_multi_tab.py
aiqc/tests/tf_reg_tab.py
aiqc/tests/torch_bin_img.py
aiqc/tests/torch_bin_seq.py
aiqc/tests/torch_bin_tab.py
aiqc/tests/torch_multi_tab.py
aiqc/tests/torch_reg_tab.py
aiqc/utils/__init__.py
aiqc/utils/config.py
aiqc/utils/dill.py
aiqc/utils/encoding.py
aiqc/utils/ingest.py
aiqc/utils/meter.py
aiqc/utils/modeling.py
aiqc/utils/pytorch.py
aiqc/utils/tensorflow.py
aiqc/utils/wrangle.py
aiqc-7.1.5.dist-info/LICENSE
aiqc-7.1.5.dist-info/METADATA
aiqc-7.1.5.dist-info/WHEEL
aiqc-7.1.5.dist-info/top_level.txt
aiqc-7.1.5.dist-info/RECORD
