Metadata-Version: 2.1
Name: aiqc
Version: 7.1.5
Summary: End-to-end machine learning on your desktop or server.
Home-page: https://aiqc.readthedocs.io/
Author: Layne Sadler
Author-email: layne.sadler@gmail.com
License: BSD 3-Clause
Classifier: Programming Language :: Python :: 3
Classifier: Natural Language :: English
Classifier: License :: OSI Approved :: BSD License
Classifier: Operating System :: OS Independent
Classifier: Development Status :: 1 - Planning
Classifier: Framework :: Jupyter
Classifier: Intended Audience :: Developers
Classifier: Topic :: Scientific/Engineering :: Artificial Intelligence
Requires-Python: >=3.5, <=3.8.12
License-File: LICENSE
Requires-Dist: tensorflow ==2.7.0
Requires-Dist: Keras ==2.7.0
Requires-Dist: h5py ==3.6.0
Requires-Dist: torch ==1.8.1
Requires-Dist: torchmetrics ==0.8.2
Requires-Dist: peewee ==3.14.3
Requires-Dist: scikit-learn ==0.24.1
Requires-Dist: numpy ==1.19.5
Requires-Dist: pandas >=1.1.0
Requires-Dist: Pillow ==8.1.2
Requires-Dist: pyarrow ==3.0.0
Requires-Dist: fastparquet ==0.7.1
Requires-Dist: plotly ==5.3.1
Requires-Dist: appdirs ==1.4.4
Requires-Dist: natsort ==7.1.1
Requires-Dist: tqdm ==4.59.0
Requires-Dist: validators ==0.18.2
Requires-Dist: dill ==0.3.3
Requires-Dist: fsspec ==0.9.0
Requires-Dist: dash ==2.5.1
Requires-Dist: dash-bootstrap-components ==1.1.0
Requires-Dist: dash-iconify ==0.1.2
Requires-Dist: importlib-metadata ==4.13.0
